CHANGES.txt
LICENSE
MANIFEST.in
README.rst
pyproject.toml
setup.cfg
setup.py
onvif/__init__.py
onvif/client.py
onvif/const.py
onvif/definition.py
onvif/exceptions.py
onvif/managers.py
onvif/settings.py
onvif/transport.py
onvif/types.py
onvif/util.py
onvif/version.txt
onvif/wrappers.py
onvif/wsa.py
onvif/wsdl/__init__.py
onvif/wsdl/accesscontrol.wsdl
onvif/wsdl/actionengine.wsdl
onvif/wsdl/addressing
onvif/wsdl/advancedsecurity.wsdl
onvif/wsdl/analytics.wsdl
onvif/wsdl/analyticsdevice.wsdl
onvif/wsdl/b-2.xsd
onvif/wsdl/bf-2.xsd
onvif/wsdl/bw-2.wsdl
onvif/wsdl/deviceio.wsdl
onvif/wsdl/devicemgmt.wsdl
onvif/wsdl/display.wsdl
onvif/wsdl/doorcontrol.wsdl
onvif/wsdl/envelope
onvif/wsdl/events.wsdl
onvif/wsdl/imaging.wsdl
onvif/wsdl/include
onvif/wsdl/media.wsdl
onvif/wsdl/onvif.xsd
onvif/wsdl/ptz.wsdl
onvif/wsdl/r-2.xsd
onvif/wsdl/receiver.wsdl
onvif/wsdl/recording.wsdl
onvif/wsdl/remotediscovery.wsdl
onvif/wsdl/replay.wsdl
onvif/wsdl/rw-2.wsdl
onvif/wsdl/search.wsdl
onvif/wsdl/t-1.xsd
onvif/wsdl/types.xsd
onvif/wsdl/ws-addr.xsd
onvif/wsdl/ws-discovery.xsd
onvif/wsdl/xml.xsd
onvif/wsdl/xmlmime
onvif_async.egg-info/PKG-INFO
onvif_async.egg-info/SOURCES.txt
onvif_async.egg-info/dependency_links.txt
onvif_async.egg-info/entry_points.txt
onvif_async.egg-info/not-zip-safe
onvif_async.egg-info/requires.txt
onvif_async.egg-info/top_level.txt