Metadata-Version: 2.1
Name: onvif-async
Version: 0.0.1
Summary: Async Python Client for ONVIF Camera
Home-page: http://github.com/hunterjm/python-onvif-zeep-async
Author: Zou Guang Yu
Author-email: zoulee24@qq.com
Maintainer: zoulee24
Maintainer-email: zoulee24@qq.com
License: MIT
Keywords: ONVIF,Camera,IPC
Platform: UNKNOWN
Requires-Python: >=3.9
License-File: LICENSE
